{"has_more":true,"quota_max":300,"quota_remaining":298,"items":[{"name":"javascript","count":1118251,"popularityChange":1010,"is_required":false,"is_moderator_only":false,"has_synonyms":true,"synonyms":["classic-javascript","javascript-alert","javascript-dom","javascript-disabled","ecmascript","js",".js","javascript-execution","vanilla-javascript","javascript-module","javascript-library","javascript-runtime"]},{"name":"java","count":1068449,"popularityChange":717,"is_required":false,"is_moderator_only":false,"has_synonyms":true,"synonyms":["java-se",".java","j2se","core-java","java-libraries","jdk","jre"]},{"name":"c#","count":947725,"popularityChange":538,"is_required":false,"is_moderator_only":false,"has_synonyms":true,"synonyms":["csharp","c#-language","c-sharp","c#.net","visual-c#",".cs-file"]},{"name":"php","count":917596,"popularityChange":595,"is_required":false,"is_moderator_only":false,"has_synonyms":true,"synonyms":["php-oop","php-errors","php-cgi","php-mail","php-functions","php-readfile","php-session","php5","php-frameworks","php-date","php.ini","hypertext-preprocessor","php-cli","php-fpm","phtml"]},{"name":"android","count":833731,"popularityChange":616,"is_required":false,"is_moderator_only":false,"has_synonyms":true,"synonyms":["android-application","android-ui","android-device","android-api","android-mobile","android-sdk","android-framework"]},{"name":"jquery","count":734147,"popularityChange":488,"is_required":false,"is_moderator_only":false,"has_synonyms":true,"synonyms":["jquery-core","jquery-live"]},{"name":"python","count":573322,"popularityChange":575,"is_required":false,"is_moderator_only":false,"has_synonyms":true,"synonyms":["python-shell","python-interpreter","pythonic"]},{"name":"html","count":533614,"popularityChange":415,"is_required":false,"is_moderator_only":false,"has_synonyms":true,"synonyms":["div","divs","nested-divs","div-layouts","span","html-comments","html-attributes","html-tag"]},{"name":"c++","count":446594,"popularityChange":214,"is_required":false,"is_moderator_only":false,"has_synonyms":true,"synonyms":["cpp"]},{"name":"ios","count":430489,"popularityChange":309,"is_required":false,"is_moderator_only":false,"has_synonyms":true,"synonyms":["iphone-os","apple-ios","ios-sdk"]},{"name":"mysql","count":395104,"popularityChange":292,"is_required":false,"is_moderator_only":false,"has_synonyms":true,"synonyms":["mysql-query","my-sql","mysql-table","mysqld","mysqlclient","mysql-server"]},{"name":"css","count":387773,"popularityChange":286,"is_required":false,"is_moderator_only":false,"has_synonyms":true,"synonyms":["cascading-style-sheet","css-layout","css-attributes","css-background-image","css-validation","style.css-template-file","box-model","css-display","css-centering","min-height","min-width","max-height","max-width","css-line-height","css-overflow","font-weight","css-box-model","alternate-stylesheets","inline-block","css-classes","css-height","css2","css-inheritance","css-columns","css-menu","css-reset"]},{"name":"sql","count":329687,"popularityChange":218,"is_required":false,"is_moderator_only":false,"has_synonyms":true,"synonyms":["select-statement","sqlselect","sql-select","sql-syntax","sql-query","sql-statement"]},{"name":"asp.net","count":288416,"popularityChange":154,"is_required":false,"is_moderator_only":false,"has_synonyms":true,"synonyms":["aspx","asp.net-website","asp-net","aspdotnet"]},{"name":"objective-c","count":258131,"popularityChange":89,"is_required":false,"is_moderator_only":false,"has_synonyms":true,"synonyms":["objc"]},{"name":"ruby-on-rails","count":242610,"popularityChange":148,"is_required":false,"is_moderator_only":false,"has_synonyms":true,"synonyms":["ror","rails"]},{"name":".net","count":231715,"popularityChange":62,"is_required":false,"is_moderator_only":false,"has_synonyms":true,"synonyms":["dot-net","dotnet",".net-framework"]},{"name":"c","count":217921,"popularityChange":87,"is_required":false,"is_moderator_only":false,"has_synonyms":false},{"name":"iphone","count":212221,"popularityChange":33,"is_required":false,"is_moderator_only":false,"has_synonyms":true,"synonyms":["iphone-development","iphone-sdk","iphone-programming","iphone-app","iphone-web","iphone-ios"]},{"name":"arrays","count":179639,"popularityChange":144,"is_required":false,"is_moderator_only":false,"has_synonyms":true,"synonyms":["javascript-array","mongodb-arrays","string-array","char-array","jsonarray","array-of-objects","array","sub-arrays","character-arrays","swift-array"]},{"name":"angularjs","count":171008,"popularityChange":272,"is_required":false,"is_moderator_only":false,"has_synonyms":true,"synonyms":["angular.js","angular"]},{"name":"sql-server","count":163822,"popularityChange":164,"is_required":false,"is_moderator_only":false,"has_synonyms":true,"synonyms":["ms-sql-server","mssql","sql-srever"]},{"name":"ruby","count":159528,"popularityChange":89,"is_required":false,"is_moderator_only":false,"has_synonyms":false},{"name":"json","count":154831,"popularityChange":163,"is_required":false,"is_moderator_only":false,"has_synonyms":true,"synonyms":["json-parsing","json-encode","json-decode"]},{"name":"ajax","count":144690,"popularityChange":116,"is_required":false,"is_moderator_only":false,"has_synonyms":true,"synonyms":[".ajax"]},{"name":"regex","count":144511,"popularityChange":83,"is_required":false,"is_moderator_only":false,"has_synonyms":true,"synonyms":["regexes","regexp","regular-expression","regular-expressions","regex-php","perl-regex","apache-regexp","regularexpression","perlre"]},{"name":"xml","count":136852,"popularityChange":85,"is_required":false,"is_moderator_only":false,"has_synonyms":true,"synonyms":["xml-file"]},{"name":"r","count":136092,"popularityChange":189,"is_required":false,"is_moderator_only":false,"has_synonyms":true,"synonyms":["rstats","r-language"]},{"name":"asp.net-mvc","count":133048,"popularityChange":83,"is_required":false,"is_moderator_only":false,"has_synonyms":true,"synonyms":["asp-mvc","aspnet-mvc","aspnet.mvc","asp.net.mvc","asp-net-mvc","asp.mvc","mvc.net"]},{"name":"linux","count":123606,"popularityChange":86,"is_required":false,"is_moderator_only":false,"has_synonyms":false},{"name":"node.js","count":121741,"popularityChange":175,"is_required":false,"is_moderator_only":false,"has_synonyms":true,"synonyms":["nodejs","io.js"]},{"name":"django","count":118779,"popularityChange":83,"is_required":false,"is_moderator_only":false,"has_synonyms":false},{"name":"wpf","count":117434,"popularityChange":55,"is_required":false,"is_moderator_only":false,"has_synonyms":false},{"name":"database","count":111237,"popularityChange":84,"is_required":false,"is_moderator_only":false,"has_synonyms":true,"synonyms":["databases","db","database-structure","dbms"]},{"name":"xcode","count":99329,"popularityChange":53,"is_required":false,"is_moderator_only":false,"has_synonyms":true,"synonyms":["xcode-ide"]},{"name":"vb.net","count":98323,"popularityChange":63,"is_required":false,"is_moderator_only":false,"has_synonyms":true,"synonyms":["vb","vbproj"]},{"name":"eclipse","count":97242,"popularityChange":55,"is_required":false,"is_moderator_only":false,"has_synonyms":false},{"name":"string","count":96468,"popularityChange":47,"is_required":false,"is_moderator_only":false,"has_synonyms":true,"synonyms":["str","string-manipulation","strings","empty-string"]},{"name":"windows","count":94590,"popularityChange":54,"is_required":false,"is_moderator_only":false,"has_synonyms":true,"synonyms":["windows-application","windows-programming"]},{"name":"swift","count":92086,"popularityChange":170,"is_required":false,"is_moderator_only":false,"has_synonyms":true,"synonyms":["swift-language","swift-ios","swift1.2"]},{"name":"excel","count":91597,"popularityChange":110,"is_required":false,"is_moderator_only":false,"has_synonyms":true,"synonyms":["workbook","ms-excel"]},{"name":"wordpress","count":91264,"popularityChange":99,"is_required":false,"is_moderator_only":false,"has_synonyms":true,"synonyms":["wordpress-permission","wp-query","wordpress-mu","wordpress-theme-customize","wordpress-plugin-dev","wordpress-filter","wordpress-widget","wordpress-loop"]},{"name":"html5","count":89868,"popularityChange":51,"is_required":false,"is_moderator_only":false,"has_synonyms":true,"synonyms":["xhtml5","time-tag"]},{"name":"spring","count":87028,"popularityChange":105,"is_required":false,"is_moderator_only":false,"has_synonyms":true,"synonyms":["spring-framework"]},{"name":"multithreading","count":84138,"popularityChange":51,"is_required":false,"is_moderator_only":false,"has_synonyms":true,"synonyms":["cross-threading","multi-threaded","threading","multithread","threads","thread"]},{"name":"facebook","count":72415,"popularityChange":34,"is_required":false,"is_moderator_only":false,"has_synonyms":true,"synonyms":["facebook-sdk-ios","facebook-connect","facebook-api","facebook-sdk","facebook-application"]},{"name":"image","count":71126,"popularityChange":35,"is_required":false,"is_moderator_only":false,"has_synonyms":true,"synonyms":["picture","pictures","img","images"]},{"name":"forms","count":70691,"popularityChange":41,"is_required":false,"is_moderator_only":false,"has_synonyms":true,"synonyms":["form"]},{"name":"git","count":70202,"popularityChange":62,"is_required":false,"is_moderator_only":false,"has_synonyms":false},{"name":"oracle","count":69732,"popularityChange":59,"is_required":false,"is_moderator_only":false,"has_synonyms":false},{"name":"bash","count":67379,"popularityChange":57,"is_required":false,"is_moderator_only":false,"has_synonyms":true,"synonyms":["bash-script","bashrc",".bashrc","bash-alias","bash-variables"]},{"name":"osx","count":67040,"popularityChange":49,"is_required":false,"is_moderator_only":false,"has_synonyms":true,"synonyms":["mac","macos","macosx"]},{"name":"winforms","count":66249,"popularityChange":32,"is_required":false,"is_moderator_only":false,"has_synonyms":true,"synonyms":["windows.forms","winform","window-form","windows-form","window-forms","windows-forms"]},{"name":"algorithm","count":64161,"popularityChange":34,"is_required":false,"is_moderator_only":false,"has_synonyms":true,"synonyms":["algorithm-design","algorithms"]},{"name":"twitter-bootstrap","count":63302,"popularityChange":66,"is_required":false,"is_moderator_only":false,"has_synonyms":false},{"name":"mongodb","count":62788,"popularityChange":64,"is_required":false,"is_moderator_only":false,"has_synonyms":true,"synonyms":["mongo","mongod"]},{"name":"apache","count":62565,"popularityChange":32,"is_required":false,"is_moderator_only":false,"has_synonyms":true,"synonyms":["httpd"]},{"name":"performance","count":61249,"popularityChange":33,"is_required":false,"is_moderator_only":false,"has_synonyms":true,"synonyms":["speed","faster","running-time","speed-up","efficiency","performance-issues","perfomance","performance-comparison","slow","fast","performance-tuning","slowness","tuning","wcf-performance","linq-performance","jquery-performance","javascript-performance","android-performance","application-performance","performance-measurement","performance-monitoring","slow-load","code-efficiency"]},{"name":"vba","count":60781,"popularityChange":64,"is_required":false,"is_moderator_only":false,"has_synonyms":true,"synonyms":["visual-basic-applications","vba-macros","macros-vba"]},{"name":"swing","count":60738,"popularityChange":22,"is_required":false,"is_moderator_only":false,"has_synonyms":true,"synonyms":["java-swing","javax.swing"]},{"name":"matlab","count":60303,"popularityChange":38,"is_required":false,"is_moderator_only":false,"has_synonyms":true,"synonyms":["matlab-path","matlab-ide","matlab-toolbox","mlint","m-file"]},{"name":"entity-framework","count":57532,"popularityChange":26,"is_required":false,"is_moderator_only":false,"has_synonyms":true,"synonyms":["linq-entity-framework","ef"]},{"name":"linq","count":56098,"popularityChange":25,"is_required":false,"is_moderator_only":false,"has_synonyms":false},{"name":"visual-studio","count":55301,"popularityChange":58,"is_required":false,"is_moderator_only":false,"has_synonyms":true,"synonyms":["vs.net","msvs"]},{"name":"ruby-on-rails-3","count":54720,"popularityChange":13,"is_required":false,"is_moderator_only":false,"has_synonyms":true,"synonyms":["rails3","ror3"]},{"name":"hibernate","count":54231,"popularityChange":44,"is_required":false,"is_moderator_only":false,"has_synonyms":false},{"name":"postgresql","count":53160,"popularityChange":63,"is_required":false,"is_moderator_only":false,"has_synonyms":true,"synonyms":["pgsql","postgres","sql-postgres"]},{"name":"list","count":52913,"popularityChange":42,"is_required":false,"is_moderator_only":false,"has_synonyms":true,"synonyms":["lists","ilist"]},{"name":"css3","count":52497,"popularityChange":47,"is_required":false,"is_moderator_only":false,"has_synonyms":true,"synonyms":["css-border-image","css-border-radius","css-box-shadow","css-text-overflow","css-text-shadow"]},{"name":"perl","count":51051,"popularityChange":27,"is_required":false,"is_moderator_only":false,"has_synonyms":false},{"name":"web-services","count":50778,"popularityChange":34,"is_required":false,"is_moderator_only":false,"has_synonyms":true,"synonyms":["web-service"]},{"name":"scala","count":50658,"popularityChange":42,"is_required":false,"is_moderator_only":false,"has_synonyms":false},{"name":"qt","count":49667,"popularityChange":36,"is_required":false,"is_moderator_only":false,"has_synonyms":false},{"name":".htaccess","count":49517,"popularityChange":32,"is_required":false,"is_moderator_only":false,"has_synonyms":true,"synonyms":["htaccess"]},{"name":"python-2.7","count":48992,"popularityChange":82,"is_required":false,"is_moderator_only":false,"has_synonyms":false},{"name":"function","count":47625,"popularityChange":25,"is_required":false,"is_moderator_only":false,"has_synonyms":true,"synonyms":["functions","def"]},{"name":"sqlite","count":47515,"popularityChange":38,"is_required":false,"is_moderator_only":false,"has_synonyms":true,"synonyms":["sqllite","sqlitedatabase"]},{"name":"visual-studio-2010","count":46156,"popularityChange":13,"is_required":false,"is_moderator_only":false,"has_synonyms":true,"synonyms":["vs2010","visual-studio-2010-rtm","msvc10"]},{"name":"sql-server-2008","count":46125,"popularityChange":22,"is_required":false,"is_moderator_only":false,"has_synonyms":true,"synonyms":["sql2008","mssql2008","ssms-2008"]},{"name":"file","count":45848,"popularityChange":28,"is_required":false,"is_moderator_only":false,"has_synonyms":true,"synonyms":["files"]},{"name":"shell","count":45418,"popularityChange":33,"is_required":false,"is_moderator_only":false,"has_synonyms":true,"synonyms":["shell-script","shell-scripting","shell-command","shell-commands","shellscript"]},{"name":"uitableview","count":45125,"popularityChange":22,"is_required":false,"is_moderator_only":false,"has_synonyms":true,"synonyms":["uitableviewcell","uitableviewcellaccessory","uitableviewcellstylevalue","uitableviewstyle","uitableviewdatasource","uitableviewdelegate","uitableviewheader","uitableviewfooter","uitableview-section","uitableviewstylegrouped","uitableviewcontroller","uitable","uitableviewcelll"]},{"name":"wcf","count":44939,"popularityChange":8,"is_required":false,"is_moderator_only":false,"has_synonyms":true,"synonyms":["wcf-service"]},{"name":"codeigniter","count":44765,"popularityChange":34,"is_required":false,"is_moderator_only":false,"has_synonyms":true,"synonyms":["codeigniter-routing","codeigniter-form-helper","codeigniter-validation","codeigniter-activerecord","codeigniter-pagination","codeigniter-url"]},{"name":"api","count":44581,"popularityChange":36,"is_required":false,"is_moderator_only":false,"has_synonyms":true,"synonyms":["apis"]},{"name":"excel-vba","count":44460,"popularityChange":60,"is_required":false,"is_moderator_only":false,"has_synonyms":true,"synonyms":["excel-macro"]},{"name":"cordova","count":43964,"popularityChange":44,"is_required":false,"is_moderator_only":false,"has_synonyms":true,"synonyms":["phonegap"]},{"name":"rest","count":43695,"popularityChange":38,"is_required":false,"is_moderator_only":false,"has_synonyms":true,"synonyms":["restful-web-services","restful"]},{"name":"google-maps","count":42869,"popularityChange":30,"is_required":false,"is_moderator_only":false,"has_synonyms":true,"synonyms":["gmaps","google-maps-api"]},{"name":"validation","count":42601,"popularityChange":26,"is_required":false,"is_moderator_only":false,"has_synonyms":true,"synonyms":["validations","validators","input-validation","form-validation","validate","validator","data-validation"]},{"name":"class","count":42354,"popularityChange":21,"is_required":false,"is_moderator_only":false,"has_synonyms":true,"synonyms":["classes"]},{"name":"maven","count":42354,"popularityChange":43,"is_required":false,"is_moderator_only":false,"has_synonyms":true,"synonyms":["mvn"]},{"name":"sockets","count":40853,"popularityChange":10,"is_required":false,"is_moderator_only":false,"has_synonyms":true,"synonyms":["bsd-sockets","socket-programming","socket"]},{"name":"unit-testing","count":40761,"popularityChange":30,"is_required":false,"is_moderator_only":false,"has_synonyms":true,"synonyms":["unit-test","unit-tests","unittest"]},{"name":"jsp","count":40144,"popularityChange":23,"is_required":false,"is_moderator_only":false,"has_synonyms":false},{"name":"symfony2","count":39957,"popularityChange":39,"is_required":false,"is_moderator_only":false,"has_synonyms":true,"synonyms":["symfony"]},{"name":"actionscript-3","count":39606,"popularityChange":6,"is_required":false,"is_moderator_only":false,"has_synonyms":true,"synonyms":["as3"]},{"name":"google-chrome","count":39554,"popularityChange":35,"is_required":false,"is_moderator_only":false,"has_synonyms":true,"synonyms":["chrome"]},{"name":"xaml","count":38881,"popularityChange":16,"is_required":false,"is_moderator_only":false,"has_synonyms":false},{"name":"asp.net-mvc-3","count":38595,"popularityChange":4,"is_required":false,"is_moderator_only":false,"has_synonyms":true,"synonyms":["asp.net-mvc-3-validation","mvc3"]}]}